fastaibreadcrumbs/__init__.py
fastaibreadcrumbs/_modidx.py
fastaibreadcrumbs/core.py
fastaibreadcrumbs-0.0.11.dist-info/LICENSE
fastaibreadcrumbs-0.0.11.dist-info/METADATA
fastaibreadcrumbs-0.0.11.dist-info/WHEEL
fastaibreadcrumbs-0.0.11.dist-info/entry_points.txt
fastaibreadcrumbs-0.0.11.dist-info/top_level.txt
fastaibreadcrumbs-0.0.11.dist-info/RECORD
