Metadata-Version: 2.1
Name: fastaibreadcrumbs
Version: 0.0.11
Summary: Breadcrumbs for fastai users
Home-page: https://github.com/sapal6/fastaibreadcrumbs/
Author: Satyabrata pal
Author-email: satyabrata.pal1@gmail.com
License: Apache Software License 2.0
Keywords: machine-learning,nbdev,fastai
Platform: UNKNOWN
Classifier: Development Status :: 3 - Alpha
Classifier: Intended Audience :: Developers
Classifier: Natural Language :: English
Classifier: Programming Language :: Python :: 3.7
Classifier: Programming Language :: Python :: 3.8
Classifier: Programming Language :: Python :: 3.9
Classifier: Programming Language :: Python :: 3.10
Classifier: License :: OSI Approved :: Apache Software License
Requires-Python: >=3.7
License-File: LICENSE
Requires-Dist: fastai
Requires-Dist: opencv-python
Requires-Dist: torchvision
Requires-Dist: fastkaggle
Provides-Extra: dev
